api2ch/__init__.py
api2ch/api.py
api2ch/captcha.py
api2ch/client.py
api2ch/exceptions.py
api2ch/helpers.py
api2ch/models.py
api2ch/settings.py
api2ch/utils.py
dvach.api-1.0.0.dist-info/LICENSE
dvach.api-1.0.0.dist-info/METADATA
dvach.api-1.0.0.dist-info/WHEEL
dvach.api-1.0.0.dist-info/top_level.txt
dvach.api-1.0.0.dist-info/RECORD
