Metadata-Version: 2.1
Name: dvach.api
Version: 1.0.0
Summary: Python 2ch.hk API wrapper
Home-page: https://github.com/anonim-legivon/dvach.api
Author: anonim-legivon
Author-email: fadedDexofan@protonmail.com
License: Apache License 2.0
Keywords: dvach 2ch 2ch.hk api wrapper
Platform: UNKNOWN
Classifier: Development Status :: 4 - Beta
Classifier: Operating System :: OS Independent
Classifier: Programming Language :: Python :: 3
Classifier: Programming Language :: Python :: 3.6
Classifier: Programming Language :: Python :: 3.7
Classifier: License :: OSI Approved :: Apache Software License
Classifier: Topic :: Internet
Requires-Python: >=3.6
Requires-Dist: requests (==2.21.0)
Requires-Dist: addict (==2.2.0)
Requires-Dist: simplejson (==3.16.0)
